pkm_python_client/__init__.py
pkm_python_client/pkm_client.py
pkm_python_client-0.1.22.dist-info/WHEEL
pkm_python_client-0.1.22.dist-info/METADATA
pkm_python_client-0.1.22.dist-info/RECORD
