Metadata-Version: 2.1
Name: pkm-python-client
Version: 0.1.22
Summary: A python client for the Decoder project's PKM server
Author: Gaël de Chalendar
Author-email: gael.de-chalendar@cea.fr
Classifier: Programming Language :: Python :: 2
Classifier: Programming Language :: Python :: 2.7
Classifier: Programming Language :: Python :: 3
Classifier: Programming Language :: Python :: 3.4
Classifier: Programming Language :: Python :: 3.5
Classifier: Programming Language :: Python :: 3.6
Classifier: Programming Language :: Python :: 3.7
Classifier: Programming Language :: Python :: 3.8
Requires-Dist: requests
